medical_data_validator/__init__.py
medical_data_validator/analytics.py
medical_data_validator/cli.py
medical_data_validator/compliance.py
medical_data_validator/compliance_templates.py
medical_data_validator/core.py
medical_data_validator/dashboard.py
medical_data_validator/extensions.py
medical_data_validator/monitoring.py
medical_data_validator/performance.py
medical_data_validator/security.py
medical_data_validator/validators.py
medical_data_validator/dashboard/__init__.py
medical_data_validator/dashboard/app.py
medical_data_validator/dashboard/dash_layout.py
medical_data_validator/dashboard/docs.py
medical_data_validator/dashboard/routes.py
medical_data_validator/dashboard/utils.py
medical_data_validator-1.2.1.dist-info/licenses/LICENSE
medical_data_validator-1.2.1.dist-info/METADATA
medical_data_validator-1.2.1.dist-info/WHEEL
medical_data_validator-1.2.1.dist-info/entry_points.txt
medical_data_validator-1.2.1.dist-info/top_level.txt
medical_data_validator-1.2.1.dist-info/RECORD
