Metadata-Version: 2.4
Name: medical-data-validator
Version: 1.2.1
Summary: A comprehensive medical data validation library for healthcare datasets
Author-email: Rana Ehtasham Ali <ranaehtashamali1@gmail.com>
Maintainer-email: Rana Ehtasham Ali <ranaehtashamali1@gmail.com>
License: MIT
Project-URL: Homepage, https://github.com/RanaEhtashamAli/medical-data-validator
Project-URL: Documentation, https://medical-data-validator.readthedocs.io/
Project-URL: Repository, https://github.com/RanaEhtashamAli/medical-data-validator
Project-URL: Bug Tracker, https://github.com/RanaEhtashamAli/medical-data-validator/issues
Project-URL: PyPI, https://pypi.org/project/medical-data-validator/
Keywords: medical,healthcare,data,validation,phi,pii,quality
Classifier: Development Status :: 4 - Beta
Classifier: Intended Audience :: Healthcare Industry
Classifier: Intended Audience :: Science/Research
Classifier: License :: OSI Approved :: MIT License
Classifier: Operating System :: OS Independent
Classifier: Programming Language :: Python :: 3
Classifier: Programming Language :: Python :: 3.8
Classifier: Programming Language :: Python :: 3.9
Classifier: Programming Language :: Python :: 3.10
Classifier: Programming Language :: Python :: 3.11
Classifier: Topic :: Scientific/Engineering :: Information Analysis
Classifier: Topic :: Software Development :: Libraries :: Python Modules
Classifier: Topic :: Text Processing :: Filters
Requires-Python: >=3.8
License-File: LICENSE
Requires-Dist: pandas>=1.5.0
Requires-Dist: pydantic>=2.0.0
Requires-Dist: numpy>=1.21.0
Requires-Dist: openpyxl>=3.0.0
Requires-Dist: requests>=2.25.0
Requires-Dist: urllib3>=1.26.0
Provides-Extra: cli
Requires-Dist: click>=8.0.0; extra == "cli"
Requires-Dist: rich>=13.0.0; extra == "cli"
Requires-Dist: tabulate>=0.9.0; extra == "cli"
Provides-Extra: web
Requires-Dist: flask>=2.3.0; extra == "web"
Requires-Dist: flask-cors>=4.0.0; extra == "web"
Requires-Dist: plotly>=5.15.0; extra == "web"
Requires-Dist: dash>=2.14.0; extra == "web"
Requires-Dist: dash-bootstrap-components>=1.5.0; extra == "web"
Requires-Dist: gunicorn>=21.0.0; extra == "web"
Requires-Dist: python-dotenv>=1.0.0; extra == "web"
Requires-Dist: werkzeug>=2.3.0; extra == "web"
Provides-Extra: api
Requires-Dist: flask>=2.3.0; extra == "api"
Requires-Dist: flask-cors>=4.0.0; extra == "api"
Requires-Dist: python-multipart>=0.0.6; extra == "api"
Requires-Dist: flask-restx>=1.1.0; extra == "api"
Requires-Dist: apispec>=6.0.0; extra == "api"
Requires-Dist: marshmallow>=3.19.0; extra == "api"
Requires-Dist: markdown>=3.4.0; extra == "api"
Provides-Extra: web-all
Requires-Dist: flask>=2.3.0; extra == "web-all"
Requires-Dist: flask-cors>=4.0.0; extra == "web-all"
Requires-Dist: plotly>=5.15.0; extra == "web-all"
Requires-Dist: dash>=2.14.0; extra == "web-all"
Requires-Dist: dash-bootstrap-components>=1.5.0; extra == "web-all"
Requires-Dist: gunicorn>=21.0.0; extra == "web-all"
Requires-Dist: python-dotenv>=1.0.0; extra == "web-all"
Requires-Dist: werkzeug>=2.3.0; extra == "web-all"
Requires-Dist: flask-restx>=1.1.0; extra == "web-all"
Requires-Dist: apispec>=6.0.0; extra == "web-all"
Requires-Dist: marshmallow>=3.19.0; extra == "web-all"
Requires-Dist: markdown>=3.4.0; extra == "web-all"
Provides-Extra: all
Requires-Dist: click>=8.0.0; extra == "all"
Requires-Dist: rich>=13.0.0; extra == "all"
Requires-Dist: tabulate>=0.9.0; extra == "all"
Requires-Dist: flask>=2.3.0; extra == "all"
Requires-Dist: flask-cors>=4.0.0; extra == "all"
Requires-Dist: plotly>=5.15.0; extra == "all"
Requires-Dist: dash>=2.14.0; extra == "all"
Requires-Dist: dash-bootstrap-components>=1.5.0; extra == "all"
Requires-Dist: gunicorn>=21.0.0; extra == "all"
Requires-Dist: python-dotenv>=1.0.0; extra == "all"
Requires-Dist: werkzeug>=2.3.0; extra == "all"
Requires-Dist: flask-restx>=1.1.0; extra == "all"
Requires-Dist: apispec>=6.0.0; extra == "all"
Requires-Dist: marshmallow>=3.19.0; extra == "all"
Requires-Dist: markdown>=3.4.0; extra == "all"
Provides-Extra: dev
Requires-Dist: pytest>=7.0.0; extra == "dev"
Requires-Dist: pytest-cov>=4.0.0; extra == "dev"
Requires-Dist: pytest-mock>=3.10.0; extra == "dev"
Requires-Dist: black>=23.0.0; extra == "dev"
Requires-Dist: isort>=5.12.0; extra == "dev"
Requires-Dist: flake8>=6.0.0; extra == "dev"
Requires-Dist: mypy>=1.0.0; extra == "dev"
Requires-Dist: bandit>=1.7.0; extra == "dev"
Requires-Dist: safety>=2.0.0; extra == "dev"
Requires-Dist: pre-commit>=3.0.0; extra == "dev"
Provides-Extra: docs
Requires-Dist: sphinx>=6.0.0; extra == "docs"
Requires-Dist: sphinx-rtd-theme>=1.2.0; extra == "docs"
Requires-Dist: myst-parser>=1.0.0; extra == "docs"
Requires-Dist: sphinx-autodoc-typehints>=1.23.0; extra == "docs"
Provides-Extra: test
Requires-Dist: pytest>=7.0.0; extra == "test"
Requires-Dist: pytest-cov>=4.0.0; extra == "test"
Requires-Dist: pytest-mock>=3.10.0; extra == "test"
Requires-Dist: pytest-benchmark>=4.0.0; extra == "test"
Requires-Dist: selenium>=4.0.0; extra == "test"
Requires-Dist: webdriver-manager>=4.0.0; extra == "test"
Requires-Dist: matplotlib>=3.3.0; extra == "test"
Requires-Dist: seaborn>=0.11.0; extra == "test"
Requires-Dist: xlrd>=2.0.0; extra == "test"
Provides-Extra: dashboard
Requires-Dist: flask>=2.3.0; extra == "dashboard"
Requires-Dist: flask-cors>=4.0.0; extra == "dashboard"
Requires-Dist: plotly>=5.15.0; extra == "dashboard"
Requires-Dist: dash>=2.14.0; extra == "dashboard"
Requires-Dist: dash-bootstrap-components>=1.5.0; extra == "dashboard"
Requires-Dist: gunicorn>=21.0.0; extra == "dashboard"
Requires-Dist: python-dotenv>=1.0.0; extra == "dashboard"
Requires-Dist: werkzeug>=2.3.0; extra == "dashboard"
Provides-Extra: real-data
Requires-Dist: requests>=2.25.0; extra == "real-data"
Requires-Dist: matplotlib>=3.3.0; extra == "real-data"
Requires-Dist: seaborn>=0.11.0; extra == "real-data"
Requires-Dist: xlrd>=2.0.0; extra == "real-data"
Requires-Dist: urllib3>=1.26.0; extra == "real-data"
Dynamic: license-file
